{
  "gitSyncId": "67252580698c850488983504_cad10478-7875-442c-a188-06aefcd9ac44",
  "id": "Wkladki_DeleteQuery",
  "pluginId": "mysql-plugin",
  "pluginType": "DB",
  "unpublishedAction": {
    "actionConfiguration": {
      "body": "DELETE FROM wkladki\n  WHERE idwkladka = {{data_table.triggeredRow.idwkladka}};",
      "encodeParamsToggle": true,
      "paginationType": "NONE",
      "pluginSpecifiedTemplates": [
        {
          "value": true
        }
      ],
      "timeoutInMillisecond": 10000
    },
    "confirmBeforeExecute": false,
    "datasource": {
      "id": "app-sigma-new",
      "isAutoGenerated": false,
      "name": "app-sigma",
      "pluginId": "mysql-plugin"
    },
    "executeOnLoad": false,
    "name": "DeleteQuery",
    "pageId": "Wkladki",
    "userSetOnLoad": false
  }
}