{
  "gitSyncId": "67252580698c850488983504_3b079200-1384-488b-a070-8e43067cf643",
  "id": "Screeny_doplata.tkanina_form",
  "pluginId": "js-plugin",
  "pluginType": "JS",
  "unpublishedAction": {
    "actionConfiguration": {
      "encodeParamsToggle": true,
      "jsArguments": [],
      "paginationType": "NONE",
      "timeoutInMillisecond": 10000
    },
    "collectionId": "Screeny_doplata",
    "confirmBeforeExecute": false,
    "datasource": {
      "isAutoGenerated": false,
      "name": "UNUSED_DATASOURCE",
      "pluginId": "js-plugin"
    },
    "dynamicBindingPathList": [
      {
        "key": "body"
      }
    ],
    "executeOnLoad": true,
    "fullyQualifiedName": "doplata.tkanina_form",
    "name": "tkanina_form",
    "pageId": "Screeny",
    "userSetOnLoad": true
  }
}