{
  "gitSyncId": "67252580698c850488983504_5c61d07d-5337-4084-ba06-164d79c2ecf9",
  "id": "Plisy_tkaniny_UpdateQuery",
  "pluginId": "mysql-plugin",
  "pluginType": "DB",
  "unpublishedAction": {
    "actionConfiguration": {
      "body": "UPDATE plisy_tkaniny SET\n\t\ttkanina = '{{update_form.fieldState.tkanina.isVisible ? update_form.formData.tkanina : update_form.sourceData.tkanina}}',\n\t\tkolekcja = '{{update_form.fieldState.kolekcja.isVisible ? update_form.formData.kolekcja : update_form.sourceData.kolekcja}}',\n    obrazek = '{{update_form.fieldState.obrazek.isVisible ? update_form.formData.obrazek : update_form.sourceData.obrazek}}'\nWHERE id_tkaninaplisa = {{data_table.selectedRow.id_tkaninaplisa}};",
      "encodeParamsToggle": true,
      "paginationType": "NONE",
      "pluginSpecifiedTemplates": [
        {
          "value": true
        }
      ],
      "timeoutInMillisecond": 10000
    },
    "confirmBeforeExecute": false,
    "datasource": {
      "id": "app-sigma",
      "isAutoGenerated": false,
      "name": "app-sigma",
      "pluginId": "mysql-plugin"
    },
    "executeOnLoad": false,
    "name": "UpdateQuery",
    "pageId": "Plisy_tkaniny",
    "userSetOnLoad": false
  }
}