{
  "gitSyncId": "67252580698c850488983504_14a165fb-5483-4cd6-94fa-d99db3fa4515",
  "id": "Plisy_wyborsolar.naped",
  "pluginId": "js-plugin",
  "pluginType": "JS",
  "unpublishedAction": {
    "actionConfiguration": {
      "encodeParamsToggle": true,
      "jsArguments": [],
      "paginationType": "NONE",
      "timeoutInMillisecond": 10000
    },
    "collectionId": "Plisy_wyborsolar",
    "confirmBeforeExecute": false,
    "datasource": {
      "isAutoGenerated": false,
      "name": "UNUSED_DATASOURCE",
      "pluginId": "js-plugin"
    },
    "dynamicBindingPathList": [
      {
        "key": "body"
      }
    ],
    "executeOnLoad": false,
    "fullyQualifiedName": "wyborsolar.naped",
    "name": "naped",
    "pageId": "Plisy",
    "userSetOnLoad": true
  }
}