{
  "gitSyncId": "67252580698c850488983504_9220b8e7-06b0-4b8f-9924-a894474a28d0",
  "id": "konfigurator-screeny Copy_doplata.kolor",
  "pluginId": "js-plugin",
  "pluginType": "JS",
  "unpublishedAction": {
    "actionConfiguration": {
      "encodeParamsToggle": true,
      "jsArguments": [],
      "paginationType": "NONE",
      "timeoutInMillisecond": 10000
    },
    "collectionId": "konfigurator-screeny Copy_doplata",
    "confirmBeforeExecute": false,
    "datasource": {
      "isAutoGenerated": false,
      "name": "UNUSED_DATASOURCE",
      "pluginId": "js-plugin"
    },
    "dynamicBindingPathList": [
      {
        "key": "body"
      }
    ],
    "executeOnLoad": false,
    "fullyQualifiedName": "doplata.kolor",
    "name": "kolor",
    "pageId": "konfigurator-screeny Copy",
    "userSetOnLoad": true
  }
}