{
  "gitSyncId": "67252580698c850488983504_05f25a86-ed12-48a0-88cd-530d203ff8a9",
  "id": "konfigurator-screeny Copy_kasujzglownej",
  "pluginId": "mysql-plugin",
  "pluginType": "DB",
  "unpublishedAction": {
    "actionConfiguration": {
      "body": "DELETE FROM inventory_main WHERE inventory_main.id_wiersz = {{tabela_screeny_inventory_id.triggeredRow.id}}\n",
      "encodeParamsToggle": true,
      "paginationType": "NONE",
      "pluginSpecifiedTemplates": [
        {
          "value": true
        }
      ],
      "timeoutInMillisecond": 10000
    },
    "confirmBeforeExecute": false,
    "datasource": {
      "id": "app-sigma-new",
      "isAutoGenerated": false,
      "name": "app-sigma",
      "pluginId": "mysql-plugin"
    },
    "dynamicBindingPathList": [
      {
        "key": "body"
      }
    ],
    "executeOnLoad": false,
    "name": "kasujzglownej",
    "pageId": "konfigurator-screeny Copy",
    "userSetOnLoad": false
  }
}